yieldcurveml/__init__.py
yieldcurveml/deterministicshift/shift.py
yieldcurveml/interpolatecurve/__init__.py
yieldcurveml/interpolatecurve/interpolatecurve.py
yieldcurveml/stripcurve/__init__.py
yieldcurveml/stripcurve/bootstrapcurve.py
yieldcurveml/stripcurve/stripcurve.py
yieldcurveml/utils/__init__.py
yieldcurveml/utils/datastructures.py
yieldcurveml/utils/kernels.py
yieldcurveml/utils/utils.py
yieldcurveml-0.3.1.dist-info/METADATA
yieldcurveml-0.3.1.dist-info/WHEEL
yieldcurveml-0.3.1.dist-info/entry_points.txt
yieldcurveml-0.3.1.dist-info/licenses/LICENSE
yieldcurveml-0.3.1.dist-info/RECORD
