Metadata-Version: 2.4
Name: yieldcurveml
Version: 0.3.1
Summary: Add your description here
Author-email: "T. Moudiki" <thierry.moudiki@gmail.com>
License-File: LICENSE
Requires-Python: >=3.9
Requires-Dist: matplotlib>=3.1.3
Requires-Dist: nnetsauce>=0.29.5
Requires-Dist: numpy<2.0.0
Requires-Dist: scikit-learn>=1.0.0
Requires-Dist: scipy
Requires-Dist: tabulate
